wrapper_rabbitmq_client/__init__.py
wrapper_rabbitmq_client/rabbitmq.py
wrapper_rabbitmq_client-0.0.3.dist-info/LICENSE
wrapper_rabbitmq_client-0.0.3.dist-info/METADATA
wrapper_rabbitmq_client-0.0.3.dist-info/WHEEL
wrapper_rabbitmq_client-0.0.3.dist-info/top_level.txt
wrapper_rabbitmq_client-0.0.3.dist-info/RECORD
