Metadata-Version: 2.1
Name: wrapper-rabbitmq-client
Version: 0.0.3
Summary: Wrapper for RabbitMQ client
Home-page: UNKNOWN
Author: Tatianno Alves
Author-email: tferreiraalves@gmail.com
License: MIT License
Keywords: asterisk ami rabbitmq producer
Platform: UNKNOWN
Requires-Dist: pika
Requires-Dist: wheel
